CHANGES.rst
MANIFEST.in
README.rst
setup.py
django_zap.egg-info/PKG-INFO
django_zap.egg-info/SOURCES.txt
django_zap.egg-info/dependency_links.txt
django_zap.egg-info/not-zip-safe
django_zap.egg-info/requires.txt
django_zap.egg-info/top_level.txt
zap/__init__.py
zap/exceptions.py
zap/models.py
zap/backends/__init__.py
zap/backends/base.py
zap/backends/postgresql.py
zap/management/__init__.py
zap/management/commands/__init__.py
zap/management/commands/zap_and_create_db.py