Metadata-Version: 1.1
Name: django-zap
Version: 0.0.3
Summary: Automate the destruction and re-creation of django databases
Home-page: https://www.isotoma.com/open-source/
Author: Alex Holmes
Author-email: alex.holmes@isotoma.com
License: Apache Software License
Keywords: django isotoma zap
Platform: UNKNOWN
Classifier: Framework :: Django
Classifier: Programming Language :: Python
Classifier: Environment :: Web Environment
